README.md
requirements.txt
setup.py
openshiftx/__init__.py
openshiftx/api.py
openshiftx/node.py
openshiftx/pod.py
openshiftx/token_cache.py
openshiftx.egg-info/PKG-INFO
openshiftx.egg-info/SOURCES.txt
openshiftx.egg-info/dependency_links.txt
openshiftx.egg-info/requires.txt
openshiftx.egg-info/top_level.txt