Metadata-Version: 1.1
Name: openshiftx
Version: 0.0.0.5
Summary: OpenShift python api sdk
Home-page: https://github.com/xhuaustc/openshift-sdk-python.git
Author: xhua
Author-email: pxhua@aliyun.com
License: Apache License Version 2.0
Keywords: OpenAPI,Kubernetes,OpenShift
Platform: UNKNOWN
Classifier: Development Status :: 3 - Alpha
Classifier: Intended Audience :: Developers
Classifier: Intended Audience :: Information Technology
Classifier: License :: OSI Approved :: Apache Software License
Classifier: Operating System :: OS Independent
Classifier: Programming Language :: Python
Classifier: Programming Language :: Python :: 2
Classifier: Programming Language :: Python :: 2.7
